cabinets/__init__.py
cabinets/logger.py
cabinets/plugins.py
cabinets/cabinet/__init__.py
cabinets/cabinet/file_cabinet.py
cabinets/cabinet/s3_cabinet.py
cabinets/parser/__init__.py
cabinets/parser/csv_parser.py
cabinets/parser/json_parser.py
cabinets/parser/pickle_parser.py
cabinets/parser/plain_text_parser.py
cabinets/parser/yaml_parser.py
cabinets-0.7.0.dist-info/LICENSE
cabinets-0.7.0.dist-info/METADATA
cabinets-0.7.0.dist-info/WHEEL
cabinets-0.7.0.dist-info/top_level.txt
cabinets-0.7.0.dist-info/RECORD
