Metadata-Version: 2.1
Name: cabinets
Version: 0.7.0
Summary: A consistent approach to file operations, anywhere.
Home-page: https://github.com/lucasmlofaro/cabinets
Author: Lucas Lofaro, Sam Hollenbach
Author-email: lucasmlofaro@gmail.com, samhollenbach@gmail.com
License: GNU GPLv3+
Platform: UNKNOWN
Classifier: Development Status :: 4 - Beta
Classifier: Framework :: Pytest
Classifier: Intended Audience :: Developers
Classifier: License :: OSI Approved :: GNU General Public License v3 or later (GPLv3+)
Classifier: Operating System :: Unix
Classifier: Operating System :: MacOS :: MacOS X
Classifier: Programming Language :: Python
Classifier: Programming Language :: Python :: 3
Classifier: Programming Language :: Python :: 3 :: Only
Classifier: Programming Language :: Python :: 3.6
Classifier: Programming Language :: Python :: 3.7
Classifier: Programming Language :: Python :: 3.8
Classifier: Programming Language :: Python :: 3.9
Classifier: Programming Language :: Python :: 3.10
Requires-Python: >=3.6
License-File: LICENSE
Requires-Dist: boto3
Requires-Dist: colorama
Requires-Dist: pyYaml
Provides-Extra: test
Requires-Dist: moto (==3.0.7) ; extra == 'test'
Requires-Dist: nose ; extra == 'test'
Requires-Dist: pyfakefs ; extra == 'test'
Requires-Dist: pytest ; extra == 'test'
Requires-Dist: pytest-cov ; extra == 'test'
